LICENSE
README.md
setup.py
generic_dataset/__init__.py
generic_dataset/__version__.py
generic_dataset/data_pipeline.py
generic_dataset/dataset_folder_manager.py
generic_dataset/dataset_manager.py
generic_dataset/generic_sample.py
generic_dataset/sample_generator.py
generic_dataset.egg-info/PKG-INFO
generic_dataset.egg-info/SOURCES.txt
generic_dataset.egg-info/dependency_links.txt
generic_dataset.egg-info/requires.txt
generic_dataset.egg-info/top_level.txt
generic_dataset/utilities/__init__.py
generic_dataset/utilities/color.py
generic_dataset/utilities/engine_selector.py
generic_dataset/utilities/save_load_methods.py
tests/test_color.py
tests/test_dataset_folder_manager.py
tests/test_dataset_manager.py
tests/test_engine_selector.py
tests/test_generated_sample.py
tests/test_gpu.py
tests/test_load_save_methods.py
tests/test_pipeline.py
tests/test_sample_generator.py