Metadata-Version: 2.1
Name: generic-dataset
Version: 1.5.3
Summary: Gibson dataset
Home-page: https://github.com/micheleantonazzi/generic-dataset
Author: Michele Antonazzi
Author-email: micheleantonazzi@gmail.com
License: MIT
Classifier: Environment :: GPU :: NVIDIA CUDA
Classifier: License :: OSI Approved :: MIT License
Classifier: Programming Language :: Python :: 3
License-File: LICENSE
Requires-Dist: opencv-python<4.7; python_version == "3.6"
Requires-Dist: opencv-python; python_version > "3.6"
Requires-Dist: numpy
Requires-Dist: pandas
Requires-Dist: termcolor
Requires-Dist: stub-generator
Provides-Extra: test
Requires-Dist: pytest; extra == "test"
Requires-Dist: pytest-cov; extra == "test"
Requires-Dist: opencv-python; extra == "test"
